[
  {
    "q": "The solutions of x² + 9 = 0 are",
    "type": "mcq",
    "a": ["3", "-3", "±3", "±3i"],
    "c": 3
  },
  {
    "q": "The solutions of x² + 2x + 5 = 0 are",
    "type": "mcq",
    "a": ["1 ± 2i", "±1 + 2i", "-1 ± 2i", "±2i"],
    "c": 2
  },
  {
    "q": "The value of i²⁴ is equal to",
    "type": "mcq",
    "a": ["1", "-1", "-i", "i"],
    "c": 0
  },
  {
    "q": "i⁴¹ + i⁴² + i⁴³ + i⁴⁴ =",
    "type": "mcq",
    "a": ["i", "0", "-i", "-42"],
    "c": 1
  },
  {
    "q": "i⁷³ + 1/i¹⁰⁰ =",
    "type": "mcq",
    "a": ["1 + i", "1 - i", "i", "-i"],
    "c": 0
  },
  {
    "q": "If n is a positive integer, then the value of (i⁴ⁿ⁺¹ - i⁴ⁿ⁻¹)/2 equals",
    "type": "mcq",
    "a": ["1", "-1", "i", "2i"],
    "c": 2
  },
  {
    "q": "The value of i⁶⁴ is",
    "type": "mcq",
    "a": ["i", "-i", "1", "-1"],
    "c": 2
  },
  {
    "q": "The solutions of x² + 25 = 0 are",
    "type": "mcq",
    "a": ["±5", "5", "-5", "±5i"],
    "c": 3
  },
  {
    "q": "The solutions of 2x² + 3 = 0 are",
    "type": "mcq",
    "a": ["±3/2", "±(3/2)i", "±(√3/2)i", "±(√6/2)i"],
    "c": 3
  },
  {
    "q": "The solutions of -x² - 1 = 0 are",
    "type": "mcq",
    "a": ["±1", "±i", "1 ± i", "0"],
    "c": 1
  }
]
